verif/__init__.py
verif/aggregator.py
verif/axis.py
verif/data.py
verif/driver.py
verif/field.py
verif/input.py
verif/interval.py
verif/location.py
verif/metric.py
verif/metric_type.py
verif/output.py
verif/util.py
verif/variable.py
verif/version.py
verif-1.3.0.dist-info/LICENSE
verif-1.3.0.dist-info/METADATA
verif-1.3.0.dist-info/WHEEL
verif-1.3.0.dist-info/entry_points.txt
verif-1.3.0.dist-info/top_level.txt
verif-1.3.0.dist-info/RECORD
