Metadata-Version: 2.1
Name: verif
Version: 1.3.0
Summary: A verification program for meteorological forecasts and observations
Home-page: https://github.com/WFRT/verif
Author: Thomas Nipen
Author-email: thomas.nipen@met.no
License: BSD-3
Keywords: meteorology verification weather prediction
Platform: UNKNOWN
Classifier: Development Status :: 5 - Production/Stable
Classifier: Intended Audience :: Science/Research
Classifier: Topic :: Scientific/Engineering :: Atmospheric Science
Classifier: Topic :: Scientific/Engineering :: Information Analysis
Classifier: License :: OSI Approved :: BSD License
Classifier: Programming Language :: Python :: 3.6
Classifier: Programming Language :: Python :: 3.7
Classifier: Programming Language :: Python :: 3.8
Classifier: Programming Language :: Python :: 3.9
Classifier: Programming Language :: Python :: 3.10
Classifier: Programming Language :: Python :: 3.11
License-File: LICENSE
Requires-Dist: future
Requires-Dist: matplotlib
Requires-Dist: netCDF4
Requires-Dist: numpy (>=1.7)
Requires-Dist: scipy
Requires-Dist: six
Provides-Extra: cartopy
Requires-Dist: cartopy ; extra == 'cartopy'
Provides-Extra: test
Requires-Dist: coverage ; extra == 'test'
Requires-Dist: pep8 ; extra == 'test'
Requires-Dist: pylint ; extra == 'test'
